Workbook

Sheet PROJECT DATA
A1: Project ID | B1: Project | C1: Region | D1: UNIQUE REGIONS | E1: Project Manager | F1: Start Date | G1: End Date | H1: MONTH | I1: UNIQUE MONTH | J1: REVENUE BY MONTH | K1: Budget ₦M | L1: ACTUAL COST BY MONTH | M1: PROFIT BY MONTH | N1: Actual Cost ₦M | O1: Revenue ₦M | P1: Planned Progress % | Q1: Actual Progress % | R1: Labour Cost ₦M | S1: Material Cost ₦M | T1: Client Rating | U1: Staff | W1: PROFIT ₦M | X1: PROFIT MARGIN | Y1: BUDGET VARIANCE (NM) | Z1: PROGRESS VARIANCE | AA1: COST EFFICIENCY | AB1: LABOUR COST % | AC1: MATERIAL COST % | AD1: PROJECT STATUS
A2: P009 | B2: Abuja Stadium | C2: Abuja | D2: {=_xlfn.UNIQUE(C2:C16)} -> Abuja | E2: King | F2: 45734 | G2: 46068 | H2: =TEXT(F2,"MMMM") -> March | I2: {=_xlfn.UNIQUE(H2:H16)} -> March | J2: =SUMIF(H2:H16,"MARCH",K2:K16) -> 1240 | K2: 500 | L2: =SUMIF(_xlfn.ANCHORARRAY($I$2),"march",$N$2:$N$16) -> 485 | M2: =SUMIF(_xlfn.ANCHORARRAY($I$2),"MARCH",$W$2:$W$16) -> 125 | N2: 485 | O2: 610 | P2: 82 | Q2: 85 | R2: 135 | S2: 195 | T2: 4.3 | U2: 105 | W2: =O2-N2 -> 125 | X2: =W2/O2 -> 0.20491803 | Y2: =K2-N2 -> 15 | Z2: =Q2-P2 -> 3 | AA2: =O2/N2 -> 1.257732 | AB2: =R2/N2 -> 0.27835052 | AC2: =S2/N2 -> 0.40206186 | AD2: =IF(OR(Z2<-5,Y2<-20),"CRITICAL",IF(OR(Z2<0,Y2<0),"ATTENTION","HEALTHY")) -> HEALTHY
A3: P007 | B3: Abuja Airport | C3: Abuja | D3: Lagos | E3: Danladi | F3: 45667 | G3: 46011 | H3: =TEXT(F3,"MMMM") -> January | I3: January | J3: =SUMIF($H$2:$H$16,"January",$K$2:$K$16) -> 955 | K3: 450 | L3: =SUMIF(_xlfn.ANCHORARRAY($I$2),"january",$N$2:$N$16) -> 430 | M3: =SUMIF(_xlfn.ANCHORARRAY($I$2),"JANUARY",$W$2:$W$16) -> 110 | N3: 430 | O3: 540 | P3: 98 | Q3: 96 | R3: 120 | S3: 175 | T3: 4.8 | U3: 90 | W3: =O3-N3 -> 110 | X3: =W3/O3 -> 0.2037037 | Y3: =K3-N3 -> 20 | Z3: =Q3-P3 -> -2 | AA3: =O3/N3 -> 1.255814 | AB3: =R3/N3 -> 0.27906977 | AC3: =S3/N3 -> 0.40697674 | AD3: =IF(OR(Z3<-5,Y3<-20),"CRITICAL",IF(OR(Z3<0,Y3<0),"ATTENTION","HEALTHY")) -> ATTENTION
A4: P014 | B4: Lekki Towers | C4: Lagos | D4: Kano | E4: Emeka | F4: 45717 | G4: 46068 | H4: =TEXT(F4,"MMMM") -> March | I4: February | J4: =SUMIF($H$2:$H$16,"February",$K$2:$K$16) -> 695 | K4: 420 | L4: =SUMIF(_xlfn.ANCHORARRAY($I$2),"february",$N$2:$N$16) -> 400 | M4: =SUMIF(_xlfn.ANCHORARRAY($I$2),"FEBRUARY",$W$2:$W$16) -> 110 | N4: 400 | O4: 510 | P4: 85 | Q4: 88 | R4: 110 | S4: 165 | T4: 4.5 | U4: 82 | W4: =O4-N4 -> 110 | X4: =W4/O4 -> 0.21568627 | Y4: =K4-N4 -> 20 | Z4: =Q4-P4 -> 3 | AA4: =O4/N4 -> 1.275 | AB4: =R4/N4 -> 0.275 | AC4: =S4/N4 -> 0.4125 | AD4: =IF(OR(Z4<-5,Y4<-20),"CRITICAL",IF(OR(Z4<0,Y4<0),"ATTENTION","HEALTHY")) -> HEALTHY
A5: P003 | B5: VI Bridge | C5: Lagos | D5: Enugu | E5: Okoro | F5: 45736 | G5: 45991 | H5: =TEXT(F5,"MMMM") -> March | I5: April | J5: =SUMIF($H$2:$H$16,"April",$K$2:$K$16) -> 590 | K5: 320 | L5: =SUMIF(_xlfn.ANCHORARRAY($I$2),"april",$N$2:$N$16) -> 305 | M5: =SUMIF(_xlfn.ANCHORARRAY($I$2),"APRIL",$W$2:$W$16) -> 85 | N5: 305 | O5: 390 | P5: 90 | Q5: 94 | R5: 85 | S5: 120 | T5: 4.7 | U5: 65 | W5: =O5-N5 -> 85 | X5: =W5/O5 -> 0.21794872 | Y5: =K5-N5 -> 15 | Z5: =Q5-P5 -> 4 | AA5: =O5/N5 -> 1.2786885 | AB5: =R5/N5 -> 0.27868852 | AC5: =S5/N5 -> 0.39344262 | AD5: =IF(OR(Z5<-5,Y5<-20),"CRITICAL",IF(OR(Z5<0,Y5<0),"ATTENTION","HEALTHY")) -> HEALTHY
A6: P012 | B6: Kano Hospital | C6: Kano | E6: Garba | F6: 45713 | G6: 46001 | H6: =TEXT(F6,"MMMM") -> February | I6: May | J6: =SUMIF($H$2:$H$16,"MAy",$K$2:$K$16) -> 420 | K6: 275 | L6: =SUMIF(_xlfn.ANCHORARRAY($I$2),"may",$N$2:$N$16) -> 260 | M6: =SUMIF(_xlfn.ANCHORARRAY($I$2),"MAY",$W$2:$W$16) -> 80 | N6: 260 | O6: 340 | P6: 88 | Q6: 90 | R6: 70 | S6: 105 | T6: 4.6 | U6: 60 | W6: =O6-N6 -> 80 | X6: =W6/O6 -> 0.23529412 | Y6: =K6-N6 -> 15 | Z6: =Q6-P6 -> 2 | AA6: =O6/N6 -> 1.3076923 | AB6: =R6/N6 -> 0.26923077 | AC6: =S6/N6 -> 0.40384615 | AD6: =IF(OR(Z6<-5,Y6<-20),"CRITICAL",IF(OR(Z6<0,Y6<0),"ATTENTION","HEALTHY")) -> HEALTHY
A7: P013 | B7: Abuja Mall | C7: Abuja | E7: Ibrahim | F7: 45757 | G7: 46052 | H7: =TEXT(F7,"MMMM") -> April | I7: June | J7: =SUMIF($H$2:$H$16,"june",$K$2:$K$16) -> 150 | K7: 380 | L7: =SUMIF(_xlfn.ANCHORARRAY($I$2),"june",$N$2:$N$16) -> 395 | M7: =SUMIF(_xlfn.ANCHORARRAY($I$2),"JUNE",$W$2:$W$16) -> 65 | N7: 395 | O7: 460 | P7: 78 | Q7: 74 | R7: 105 | S7: 155 | T7: 3.9 | U7: 80 | W7: =O7-N7 -> 65 | X7: =W7/O7 -> 0.14130435 | Y7: =K7-N7 -> -15 | Z7: =Q7-P7 -> -4 | AA7: =O7/N7 -> 1.164557 | AB7: =R7/N7 -> 0.26582278 | AC7: =S7/N7 -> 0.39240506 | AD7: =IF(OR(Z7<-5,Y7<-20),"CRITICAL",IF(OR(Z7<0,Y7<0),"ATTENTION","HEALTHY")) -> ATTENTION
A8: P001 | B8: Lekki Hospital | C8: Lagos | E8: Adewale | F8: 45662 | G8: 46011 | H8: =TEXT(F8,"MMMM") -> January | K8: 180 | N8: 165 | O8: 220 | P8: 95 | Q8: 92 | R8: 48 | S8: 62 | T8: 4.5 | U8: 42 | W8: =O8-N8 -> 55 | X8: =W8/O8 -> 0.25 | Y8: =K8-N8 -> 15 | Z8: =Q8-P8 -> -3 | AA8: =O8/N8 -> 1.3333333 | AB8: =R8/N8 -> 0.29090909 | AC8: =S8/N8 -> 0.37575758 | AD8: =IF(OR(Z8<-5,Y8<-20),"CRITICAL",IF(OR(Z8<0,Y8<0),"ATTENTION","HEALTHY")) -> ATTENTION
A9: P005 | B9: Enugu Estate | C9: Enugu | E9: Obi | F9: 45755 | G9: 46068 | H9: =TEXT(F9,"MMMM") -> April | K9: 210 | N9: 198 | O9: 250 | P9: 80 | Q9: 82 | R9: 55 | S9: 82 | T9: 4.2 | U9: 50 | W9: =O9-N9 -> 52 | X9: =W9/O9 -> 0.208 | Y9: =K9-N9 -> 12 | Z9: =Q9-P9 -> 2 | AA9: =O9/N9 -> 1.2626263 | AB9: =R9/N9 -> 0.27777778 | AC9: =S9/N9 -> 0.41414141 | AD9: =IF(OR(Z9<-5,Y9<-20),"CRITICAL",IF(OR(Z9<0,Y9<0),"ATTENTION","HEALTHY")) -> HEALTHY
A10: P008 | B10: Lekki Mall | C10: Lagos | E10: Udo | F10: 45710 | G10: 46052 | H10: =TEXT(F10,"MMMM") -> February | K10: 170 | N10: 160 | O10: 210 | P10: 88 | Q10: 91 | R10: 42 | S10: 65 | T10: 4.6 | U10: 38 | W10: =O10-N10 -> 50 | X10: =W10/O10 -> 0.23809524 | Y10: =K10-N10 -> 10 | Z10: =Q10-P10 -> 3 | AA10: =O10/N10 -> 1.3125 | AB10: =R10/N10 -> 0.2625 | AC10: =S10/N10 -> 0.40625 | AD10: =IF(OR(Z10<-5,Y10<-20),"CRITICAL",IF(OR(Z10<0,Y10<0),"ATTENTION","HEALTHY")) -> HEALTHY
A11: P015 | B11: Enugu Road | C11: Enugu | E11: Chukwu | F11: 45792 | G11: 45991 | H11: =TEXT(F11,"MMMM") -> May | K11: 130 | N11: 118 | O11: 165 | P11: 95 | Q11: 97 | R11: 32 | S11: 45 | T11: 4.7 | U11: 28 | W11: =O11-N11 -> 47 | X11: =W11/O11 -> 0.28484848 | Y11: =K11-N11 -> 12 | Z11: =Q11-P11 -> 2 | AA11: =O11/N11 -> 1.3983051 | AB11: =R11/N11 -> 0.27118644 | AC11: =S11/N11 -> 0.38135593 | AD11: =IF(OR(Z11<-5,Y11<-20),"CRITICAL",IF(OR(Z11<0,Y11<0),"ATTENTION","HEALTHY")) -> HEALTHY
A12: P010 | B12: Enugu Hotel | C12: Enugu | E12: Paul | F12: 45813 | G12: 46132 | H12: =TEXT(F12,"MMMM") -> June | K12: 150 | N12: 142 | O12: 185 | P12: 70 | Q12: 72 | R12: 38 | S12: 55 | T12: 4 | U12: 35 | W12: =O12-N12 -> 43 | X12: =W12/O12 -> 0.23243243 | Y12: =K12-N12 -> 8 | Z12: =Q12-P12 -> 2 | AA12: =O12/N12 -> 1.3028169 | AB12: =R12/N12 -> 0.26760563 | AC12: =S12/N12 -> 0.38732394 | AD12: =IF(OR(Z12<-5,Y12<-20),"CRITICAL",IF(OR(Z12<0,Y12<0),"ATTENTION","HEALTHY")) -> HEALTHY
A13: P006 | B13: Ikeja Offices | C13: Lagos | E13: James | F13: 45778 | G13: 46111 | H13: =TEXT(F13,"MMMM") -> May | K13: 290 | N13: 310 | O13: 350 | P13: 75 | Q13: 68 | R13: 92 | S13: 128 | T13: 3.8 | U13: 72 | W13: =O13-N13 -> 40 | X13: =W13/O13 -> 0.11428571 | Y13: =K13-N13 -> -20 | Z13: =Q13-P13 -> -7 | AA13: =O13/N13 -> 1.1290323 | AB13: =R13/N13 -> 0.29677419 | AC13: =S13/N13 -> 0.41290323 | AD13: =IF(OR(Z13<-5,Y13<-20),"CRITICAL",IF(OR(Z13<0,Y13<0),"ATTENTION","HEALTHY")) -> CRITICAL
A14: P004 | B14: Kano School | C14: Kano | E14: Bello | F14: 45672 | G14: 45955 | H14: =TEXT(F14,"MMMM") -> January | K14: 95 | N14: 88 | O14: 120 | P14: 100 | Q14: 98 | R14: 24 | S14: 35 | T14: 4.4 | U14: 30 | W14: =O14-N14 -> 32 | X14: =W14/O14 -> 0.26666667 | Y14: =K14-N14 -> 7 | Z14: =Q14-P14 -> -2 | AA14: =O14/N14 -> 1.3636364 | AB14: =R14/N14 -> 0.27272727 | AC14: =S14/N14 -> 0.39772727 | AD14: =IF(OR(Z14<-5,Y14<-20),"CRITICAL",IF(OR(Z14<0,Y14<0),"ATTENTION","HEALTHY")) -> ATTENTION
A15: P011 | B15: Lagos Estate | C15: Lagos | E15: Adeyemi | F15: 45669 | G15: 45976 | H15: =TEXT(F15,"MMMM") -> January | K15: 230 | N15: 245 | O15: 275 | P15: 92 | Q15: 86 | R15: 65 | S15: 100 | T15: 4.1 | U15: 55 | W15: =O15-N15 -> 30 | X15: =W15/O15 -> 0.10909091 | Y15: =K15-N15 -> -15 | Z15: =Q15-P15 -> -6 | AA15: =O15/N15 -> 1.122449 | AB15: =R15/N15 -> 0.26530612 | AC15: =S15/N15 -> 0.40816327 | AD15: =IF(OR(Z15<-5,Y15<-20),"CRITICAL",IF(OR(Z15<0,Y15<0),"ATTENTION","HEALTHY")) -> CRITICAL
A16: P002 | B16: Abuja Highway | C16: Abuja | E16: Musa | F16: 45700 | G16: 46037 | H16: =TEXT(F16,"MMMM") -> February | K16: 250 | N16: 270 | O16: 285 | P16: 85 | Q16: 79 | R16: 72 | S16: 105 | T16: 4.1 | U16: 58 | W16: =O16-N16 -> 15 | X16: =W16/O16 -> 0.052631579 | Y16: =K16-N16 -> -20 | Z16: =Q16-P16 -> -6 | AA16: =O16/N16 -> 1.0555556 | AB16: =R16/N16 -> 0.26666667 | AC16: =S16/N16 -> 0.38888889 | AD16: =IF(OR(Z16<-5,Y16<-20),"CRITICAL",IF(OR(Z16<0,Y16<0),"ATTENTION","HEALTHY")) -> CRITICAL

Sheet ANALYSIS
A1: Project ID | C1: DYNNAMIC CHART DATA | F1: ITEMS | G1: RESULTS | I1: UNIQUE MONTH | J1: REVENUE | K1: ACTUAL COST | L1: PROFIT | N1: ITEMS | O1: AMOUNT | Q1: Project | R1: Actual Cost ₦M | S1: Revenue ₦M | T1: Staff | V1: REGION | W1: Revenue ₦M | Y1: Project | Z1: Over-Budget ₦M | AA1: Cumulative % | AB1: 0.8 | AE1: PERFORMANCE HEAT MAP
A2: P001 | C2: SELECTED PROJECT | D2: DROP DOWN | F2: TOTAL REVENUE (NM) | G2: =SUM('PROJECT DATA'!O2:O16) -> 4910 | I2: {=_xlfn.ANCHORARRAY('PROJECT DATA'!I2)} -> March | J2: ='PROJECT DATA'!J2 -> 1240 | K2: {='PROJECT DATA'!L2:L7} -> 485 | L2: {='PROJECT DATA'!M2:M7} -> 125 | N2: TOTAL REVENUE (NM) | O2: =G2 -> 4910 | Q2: Abuja Stadium | R2: 485 | S2: 610 | T2: 105 | V2: ='PROJECT DATA'!D2 -> Abuja | W2: =SUMIF('PROJECT DATA'!$C$2:$C$16,"ABUJA",'PROJECT DATA'!$O$2:$O$16) -> 1895 | Y2: Abuja Highway | Z2: 20 | AA2: 0.2857 | AB2: 0.8 | AE2: REGION | AF2: Revenue ₦M | AG2: PROFIT ₦M | AH2: MARGIN | AI2: CLIENT RATING
A3: P002 | C3: PROJECT ID | D3: P001 | F3: TOTAL ACTUAL COST (NM) | G3: =SUM('PROJECT DATA'!N2:N16) -> 3971 | I3: January | J3: ='PROJECT DATA'!J3 -> 955 | K3: 430 | L3: 110 | N3: TOTAL ACTUAL COST (NM) | O3: =-G3 -> -3971 | Q3: Abuja Airport | R3: 430 | S3: 540 | T3: 90 | V3: ='PROJECT DATA'!D3 -> Lagos | W3: =SUMIF('PROJECT DATA'!$C$2:$C$16,"LAGOS",'PROJECT DATA'!$O$2:$O$16) -> 1955 | Y3: Ikeja Offices | Z3: 20 | AA3: 0.5714 | AB3: 0.8 | AE3: ABUJA | AF3: =SUMIF('PROJECT DATA'!$C$2:$C$16,"ABUJA",'PROJECT DATA'!$O$2:$O$16) -> 1895 | AG3: =SUMIF('PROJECT DATA'!$C$2:$C$16,"ABUJA",'PROJECT DATA'!$W$2:$W$16) -> 315 | AH3: =AG3/AF3 -> 0.16622691 | AI3: =AVERAGEIF('PROJECT DATA'!$C$2:$C$16,"ABUJA",'PROJECT DATA'!$T$2:$T$16) -> 4.275
A4: P003 | C4: AMOUNT | D4: ₦M | F4: TOTAL PROFIT (NM) | G4: =SUM('PROJECT DATA'!W2:W16) -> 939 | I4: February | J4: ='PROJECT DATA'!J4 -> 695 | K4: 400 | L4: 110 | N4: TOTAL PROFIT (NM) | O4: =G4 -> 939 | Q4: Lekki Towers | R4: 400 | S4: 510 | T4: 82 | V4: ='PROJECT DATA'!D4 -> Kano | W4: =SUMIF('PROJECT DATA'!$C$2:$C$16,"KANO",'PROJECT DATA'!$O$2:$O$16) -> 460 | Y4: Lagos Estate | Z4: 15 | AA4: 0.7857 | AB4: 0.8 | AE4: LAGOS | AF4: =SUMIF('PROJECT DATA'!$C$2:$C$16,"LAGOS",'PROJECT DATA'!$O$2:$O$16) -> 1955 | AG4: =SUMIF('PROJECT DATA'!$C$2:$C$16,"LAGOS",'PROJECT DATA'!$W$2:$W$16) -> 370 | AH4: =AG4/AF4 -> 0.18925831 | AI4: =AVERAGEIF('PROJECT DATA'!$C$2:$C$16,"LAGOS",'PROJECT DATA'!$T$2:$T$16) -> 4.3666667
A5: P004 | C5: REVENUE | D5: =_xlfn.XLOOKUP(ANALYSIS!$D$3,'PROJECT DATA'!$A$2:$A$16,'PROJECT DATA'!$O$2:$O$16) -> 220 | F5: AVERAGE PROFIT MARGIN | G5: =AVERAGE('PROJECT DATA'!X2:X16) -> 0.19832708 | I5: April | J5: ='PROJECT DATA'!J5 -> 590 | K5: 305 | L5: 85 | Q5: VI Bridge | R5: 305 | S5: 390 | T5: 65 | V5: ='PROJECT DATA'!D5 -> Enugu | W5: =SUMIF('PROJECT DATA'!$C$2:$C$16,"ENUGU",'PROJECT DATA'!$O$2:$O$16) -> 600 | Y5: Abuja Mall | Z5: 15 | AA5: 1 | AB5: 0.8 | AE5: KANO | AF5: =SUMIF('PROJECT DATA'!$C$2:$C$16,"KANO",'PROJECT DATA'!$O$2:$O$16) -> 460 | AG5: =SUMIF('PROJECT DATA'!$C$2:$C$16,"KANO",'PROJECT DATA'!$W$2:$W$16) -> 112 | AH5: =AG5/AF5 -> 0.24347826 | AI5: =AVERAGEIF('PROJECT DATA'!$C$2:$C$16,"KANO",'PROJECT DATA'!$T$2:$T$16) -> 4.5
A6: P005 | C6: ACTUAL COST | D6: =_xlfn.XLOOKUP(ANALYSIS!$D$3,'PROJECT DATA'!$A$2:$A$16,'PROJECT DATA'!$N$2:$N$16) -> 165 | F6: PROJECTS OVER BUDGET | G6: =COUNTIF('PROJECT DATA'!Y2:Y16,"<0") -> 4 | I6: May | J6: ='PROJECT DATA'!J6 -> 420 | K6: 260 | L6: 80 | Q6: Kano Hospital | R6: 260 | S6: 340 | T6: 60 | AE6: ENUGU | AF6: =SUMIF('PROJECT DATA'!$C$2:$C$16,"ENUGU",'PROJECT DATA'!$O$2:$O$16) -> 600 | AG6: =SUMIF('PROJECT DATA'!$C$2:$C$16,"ENUGU",'PROJECT DATA'!$W$2:$W$16) -> 142 | AH6: =AG6/AF6 -> 0.23666667 | AI6: =AVERAGEIF('PROJECT DATA'!$C$2:$C$16,"ENUGU",'PROJECT DATA'!$T$2:$T$16) -> 4.3
A7: P006 | C7: PROFIT | D7: =_xlfn.XLOOKUP(ANALYSIS!$D$3,'PROJECT DATA'!$A$2:$A$16,'PROJECT DATA'!$W$2:$W$16) -> 55 | F7: AVERAGE CLIENT RATING | G7: =AVERAGE('PROJECT DATA'!T2:T16) -> 4.3466667 | I7: June | J7: ='PROJECT DATA'!J7 -> 150 | K7: 395 | L7: 65 | Q7: Abuja Mall | R7: 395 | S7: 460 | T7: 80
A8: P007 | Q8: Lekki Hospital | R8: 165 | S8: 220 | T8: 42
A9: P008 | Q9: Enugu Estate | R9: 198 | S9: 250 | T9: 50
A10: P009 | Q10: Lekki Mall | R10: 160 | S10: 210 | T10: 38
A11: P010 | Q11: Enugu Road | R11: 118 | S11: 165 | T11: 28
A12: P011 | Q12: Enugu Hotel | R12: 142 | S12: 185 | T12: 35
A13: P012 | Q13: Ikeja Offices | R13: 310 | S13: 350 | T13: 72
A14: P013 | Q14: Kano School | R14: 88 | S14: 120 | T14: 30
A15: P014 | Q15: Abuja Stadium | R15: 245 | S15: 275 | T15: 55
A16: P015 | Q16: Abuja Airport | R16: 270 | S16: 285 | T16: 58

Sheet DASHBOARD
J53: DYNAMIC CHART
